eyja_nats/__init__.py
eyja_nats/nats_hub.py
eyja_nats/nats_route.py
eyja_nats/nats_route_group.py
tests/__init__.py
tests/test_messaging/__init__.py
tests/test_messaging/test_routes.py
tests/test_messaging/test_subscribe.py
eyja_nats_hub-0.1.8.dist-info/METADATA
eyja_nats_hub-0.1.8.dist-info/WHEEL
eyja_nats_hub-0.1.8.dist-info/top_level.txt
eyja_nats_hub-0.1.8.dist-info/zip-safe
eyja_nats_hub-0.1.8.dist-info/RECORD
